botterfly/__init__.py
botterfly/bot.py
botterfly/browser/__init__.py
botterfly/browser/action/__init__.py
botterfly/browser/action/action_registry.py
botterfly/browser/action/base_action.py
botterfly/browser/action/check.py
botterfly/browser/action/click.py
botterfly/browser/action/extract.py
botterfly/browser/action/fill.py
botterfly/browser/action/go_back.py
botterfly/browser/action/go_to.py
botterfly/browser/action/wait.py
botterfly/browser/get_element.py
botterfly/browser/remote_browser.py
botterfly/config.py
botterfly/context/__init__.py
botterfly/context/context_parser.py
botterfly/context/template_renderer.py
botterfly/context/vault_wrapper.py
botterfly/plan.py
botterfly-0.3.0.dist-info/WHEEL
botterfly-0.3.0.dist-info/METADATA
botterfly-0.3.0.dist-info/RECORD
