Metadata-Version: 2.3
Name: botterfly
Version: 0.3.0
Summary: botterfly is a declarative bot use to automate task on a browser
Requires-Dist: dynaconf>=3.2.11
Requires-Dist: hvac>=2.3.0
Requires-Dist: jinja2>=3.1.6
Requires-Dist: playwright>=1.53.0
Requires-Dist: pydantic>=2.11.7
Requires-Dist: pyyaml>=6.0.2
Requires-Python: >=3.13
